igwn_accounting/__init__.py
igwn_accounting/report.py
igwn_accounting/utils.py
igwn_accounting/batch/__init__.py
igwn_accounting/batch/base.py
igwn_accounting/batch/htcondor.py
igwn_accounting/tests/__init__.py
igwn_accounting/tests/condor_history.txt
igwn_accounting/tests/test_batch_base.py
igwn_accounting/tests/test_batch_htcondor.py
igwn_accounting/tests/test_report.py
igwn_accounting/tests/test_utils.py
igwn_accounting/tests/utils.py
igwn_accounting-1.3.0.data/data/share/man/man1/igwn-accounting-report.1
igwn_accounting-1.3.0.dist-info/LICENSE
igwn_accounting-1.3.0.dist-info/METADATA
igwn_accounting-1.3.0.dist-info/WHEEL
igwn_accounting-1.3.0.dist-info/entry_points.txt
igwn_accounting-1.3.0.dist-info/top_level.txt
igwn_accounting-1.3.0.dist-info/RECORD
